opfront/__init__.py
opfront/client.py
opfront/exceptions.py
opfront/model.py
opfront/order.py
opfront/product.py
opfront/resource.py
opfront/session.py
opfront/store.py
opfront/user.py
opfront/tests/__init__.py
opfront/tests/test_client.py
opfront/tests/test_model.py
opfront/tests/test_order.py
opfront/tests/test_product.py
opfront/tests/test_resource.py
opfront/tests/test_session.py
opfront/tests/test_store.py
opfront/tests/test_user.py
opfront-1.1.1.dist-info/DESCRIPTION.rst
opfront-1.1.1.dist-info/METADATA
opfront-1.1.1.dist-info/RECORD
opfront-1.1.1.dist-info/WHEEL
opfront-1.1.1.dist-info/metadata.json
opfront-1.1.1.dist-info/top_level.txt
