Metadata-Version: 2.0
Name: opfront
Version: 1.1.1
Summary: Python SDK for the Opfront REST API
Home-page: https://github.com/opfront/python-sdk
Author: opfront
Author-email: UNKNOWN
License: MIT
Platform: UNKNOWN
Requires-Dist: requests (==2.17.3)
